{
  "goal": "Snapshot of existing code in src/extension.ts",
  "taskType": "create",
  "supersedes": [],
  "creatableFiles": ["src/extension.ts"],
  "editableFiles": [],
  "readonlyFiles": [],
  "expectedArtifacts": {
    "file": "src/extension.ts",
    "contains": [
      {
        "type": "function",
        "name": "activate",
        "args": [
          {
            "name": "context",
            "type": "vscode.ExtensionContext"
          }
        ],
        "parameters": [
          {
            "name": "context",
            "type": "vscode.ExtensionContext"
          }
        ]
      },
      {
        "type": "function",
        "name": "checkForUpdates",
        "args": [
          {
            "name": "context",
            "type": "vscode.ExtensionContext"
          },
          {
            "name": "force"
          }
        ],
        "parameters": [
          {
            "name": "context",
            "type": "vscode.ExtensionContext"
          },
          {
            "name": "force"
          }
        ]
      },
      {
        "type": "function",
        "name": "checkInstallationStatus"
      },
      {
        "type": "function",
        "name": "deactivate"
      },
      {
        "type": "function",
        "name": "detectInstallationMethod"
      },
      {
        "type": "function",
        "name": "didChange",
        "args": [
          {
            "name": "event"
          },
          {
            "name": "next"
          }
        ],
        "parameters": [
          {
            "name": "event"
          },
          {
            "name": "next"
          }
        ]
      },
      {
        "type": "function",
        "name": "didOpen",
        "args": [
          {
            "name": "document"
          },
          {
            "name": "next"
          }
        ],
        "parameters": [
          {
            "name": "document"
          },
          {
            "name": "next"
          }
        ]
      },
      {
        "type": "function",
        "name": "didSave",
        "args": [
          {
            "name": "document"
          },
          {
            "name": "next"
          }
        ],
        "parameters": [
          {
            "name": "document"
          },
          {
            "name": "next"
          }
        ]
      },
      {
        "type": "function",
        "name": "findArtifactPosition",
        "args": [
          {
            "name": "content",
            "type": "string"
          },
          {
            "name": "name",
            "type": "string"
          },
          {
            "name": "type",
            "type": "string"
          },
          {
            "name": "ext",
            "type": "string"
          }
        ],
        "parameters": [
          {
            "name": "content",
            "type": "string"
          },
          {
            "name": "name",
            "type": "string"
          },
          {
            "name": "type",
            "type": "string"
          },
          {
            "name": "ext",
            "type": "string"
          }
        ]
      },
      {
        "type": "function",
        "name": "getLatestVersion"
      },
      {
        "type": "function",
        "name": "handleDiagnostics",
        "args": [
          {
            "name": "uri"
          },
          {
            "name": "diagnostics"
          },
          {
            "name": "next"
          }
        ],
        "parameters": [
          {
            "name": "uri"
          },
          {
            "name": "diagnostics"
          },
          {
            "name": "next"
          }
        ]
      },
      {
        "type": "function",
        "name": "initializationFailedHandler",
        "args": [
          {
            "name": "error"
          }
        ],
        "parameters": [
          {
            "name": "error"
          }
        ]
      },
      {
        "type": "function",
        "name": "isNewerVersion",
        "args": [
          {
            "name": "currentVersion",
            "type": "string"
          },
          {
            "name": "newVersion",
            "type": "string"
          }
        ],
        "parameters": [
          {
            "name": "currentVersion",
            "type": "string"
          },
          {
            "name": "newVersion",
            "type": "string"
          }
        ]
      },
      {
        "type": "function",
        "name": "promptMaidLspInstall"
      },
      {
        "type": "function",
        "name": "registerCommands",
        "args": [
          {
            "name": "context",
            "type": "vscode.ExtensionContext"
          }
        ],
        "parameters": [
          {
            "name": "context",
            "type": "vscode.ExtensionContext"
          }
        ]
      },
      {
        "type": "function",
        "name": "registerNavigationProviders",
        "args": [
          {
            "name": "context",
            "type": "vscode.ExtensionContext"
          }
        ],
        "parameters": [
          {
            "name": "context",
            "type": "vscode.ExtensionContext"
          }
        ]
      },
      {
        "type": "function",
        "name": "registerTreeViews",
        "args": [
          {
            "name": "context",
            "type": "vscode.ExtensionContext"
          }
        ],
        "parameters": [
          {
            "name": "context",
            "type": "vscode.ExtensionContext"
          }
        ]
      },
      {
        "type": "function",
        "name": "registerWorkspaceListeners",
        "args": [
          {
            "name": "context",
            "type": "vscode.ExtensionContext"
          }
        ],
        "parameters": [
          {
            "name": "context",
            "type": "vscode.ExtensionContext"
          }
        ]
      },
      {
        "type": "function",
        "name": "startLanguageClient",
        "args": [
          {
            "name": "context",
            "type": "vscode.ExtensionContext"
          }
        ],
        "parameters": [
          {
            "name": "context",
            "type": "vscode.ExtensionContext"
          }
        ]
      }
    ]
  },
  "validationCommand": ["pnpm", "exec", "vitest", "run", "tests/test_task_018_extension.test.ts"]
}
